flow_modnum-0.0.35.dist-info/licenses/LICENSE
flowmodnum/__init__.py
flowmodnum/water_levels.py
flowmodnum/exe/usgarrdet.exe
flowmodnum/exe/usgbin2tab_h.exe
flowmodnum/exe/usggridlay.exe
flowmodnum/exe/usgmod2obs.exe
flowmodnum/exe/usgmod2smp.exe
flowmodnum/exe/usgquadfac.exe
flow_modnum-0.0.35.dist-info/METADATA
flow_modnum-0.0.35.dist-info/WHEEL
flow_modnum-0.0.35.dist-info/top_level.txt
flow_modnum-0.0.35.dist-info/RECORD
