Metadata-Version: 2.4
Name: flow-modnum
Version: 0.0.35
Summary: Flow Hydro Consulting's numerical modeling group Python library.
Author-email: Matias Bravo <mjbravo4@uc.cl>
License: Copyright (c) 2018 The Python Packaging Authority
Project-URL: Homepage, https://github.com/MatiasBravo1511/flow-modnum
Keywords: numerical,modeling
Classifier: License :: OSI Approved :: MIT License
Classifier: Programming Language :: Python
Classifier: Programming Language :: Python :: 3
Requires-Python: >=3.12.4
License-File: LICENSE
Requires-Dist: numpy>=1.26.4
Requires-Dist: pandas>=2.2.2
Requires-Dist: matplotlib>=3.8.4
Requires-Dist: folium>=0.18.0
Requires-Dist: plotly>=5.22.0
Requires-Dist: pyproj>=3.6.1
Requires-Dist: tqdm>=4.66.4
Requires-Dist: geopandas>=1.0.1
Requires-Dist: fiona>=1.9.6
Requires-Dist: shapely>=2.0.5
Requires-Dist: scipy>=1.13.1
Requires-Dist: scikit-image>=0.23.2
Dynamic: license-file
